spotiflow/__init__.py
spotiflow/_version.py
spotiflow/augmentations/__init__.py
spotiflow/augmentations/pipeline/__init__.py
spotiflow/augmentations/pipeline/pipeline.py
spotiflow/augmentations/test/test_pipeline.py
spotiflow/augmentations/test/transforms/test_crop.py
spotiflow/augmentations/test/transforms/test_fliprot.py
spotiflow/augmentations/test/transforms/test_intensity_shift.py
spotiflow/augmentations/test/transforms/test_noise.py
spotiflow/augmentations/test/transforms/test_rotation.py
spotiflow/augmentations/test/transforms/test_scale.py
spotiflow/augmentations/test/transforms/test_translation.py
spotiflow/augmentations/transforms/__init__.py
spotiflow/augmentations/transforms/base.py
spotiflow/augmentations/transforms/crop.py
spotiflow/augmentations/transforms/fliprot.py
spotiflow/augmentations/transforms/intensity_shift.py
spotiflow/augmentations/transforms/noise.py
spotiflow/augmentations/transforms/rotation.py
spotiflow/augmentations/transforms/scale.py
spotiflow/augmentations/transforms/translation.py
spotiflow/augmentations/transforms/utils.py
spotiflow/augmentations/transforms3d/__init__.py
spotiflow/augmentations/transforms3d/crop.py
spotiflow/augmentations/transforms3d/fliprot.py
spotiflow/augmentations/transforms3d/intensity_shift.py
spotiflow/augmentations/transforms3d/noise.py
spotiflow/augmentations/transforms3d/rotation.py
spotiflow/augmentations/transforms3d/translation.py
spotiflow/cli/__init__.py
spotiflow/cli/predict.py
spotiflow/cli/train.py
spotiflow/data/__init__.py
spotiflow/data/spots.py
spotiflow/data/spots3d.py
spotiflow/data/test/test_datasets.py
spotiflow/lib/filters.cpp
spotiflow/lib/filters.cpython-312-x86_64-linux-gnu.so
spotiflow/lib/filters3d.cpp
spotiflow/lib/filters3d.cpython-312-x86_64-linux-gnu.so
spotiflow/lib/point_nms.cpp
spotiflow/lib/point_nms.cpython-312-x86_64-linux-gnu.so
spotiflow/lib/point_nms3d.cpp
spotiflow/lib/point_nms3d.cpython-312-x86_64-linux-gnu.so
spotiflow-0.6.4.dist-info/LICENSE
spotiflow-0.6.4.dist-info/METADATA
spotiflow-0.6.4.dist-info/WHEEL
spotiflow-0.6.4.dist-info/entry_points.txt
spotiflow-0.6.4.dist-info/top_level.txt
spotiflow-0.6.4.dist-info/RECORD
spotiflow-0.6.4.dist-info/sboms/auditwheel.cdx.json
