Metadata-Version: 2.1
Name: spotiflow
Version: 0.6.4
Summary: Accurate and efficient spot detection for microscopy data
Author: Albert Dominguez Mantes, Martin Weigert
Author-email: albert.dominguezmantes@epfl.ch, martin.weigert@epfl.ch
License: BSD 3-Clause License
Classifier: Development Status :: 4 - Beta
Classifier: Intended Audience :: Science/Research
Classifier: Topic :: Scientific/Engineering
Classifier: License :: OSI Approved :: BSD License
Classifier: Programming Language :: Python :: 3.9
Classifier: Programming Language :: Python :: 3.10
Classifier: Programming Language :: Python :: 3.11
Classifier: Programming Language :: Python :: 3.12
Classifier: Programming Language :: Python :: 3.13
Classifier: Programming Language :: Python :: 3.14
Requires-Python: <3.15,>=3.9
License-File: LICENSE
Requires-Dist: configargparse
Requires-Dist: crick
Requires-Dist: csbdeep
Requires-Dist: dask
Requires-Dist: lightning
Requires-Dist: networkx
Requires-Dist: numpy
Requires-Dist: pandas
Requires-Dist: Pillow
Requires-Dist: pydash
Requires-Dist: scikit_image
Requires-Dist: scipy
Requires-Dist: setuptools
Requires-Dist: scikit-image
Requires-Dist: psutil
Requires-Dist: tensorboard
Requires-Dist: tifffile
Requires-Dist: torchvision
Requires-Dist: tqdm
Requires-Dist: typing-extensions
Requires-Dist: wandb!=0.23.1
Requires-Dist: zarr
Provides-Extra: testing
Requires-Dist: pytest; extra == "testing"
Requires-Dist: pytest-cov; extra == "testing"
Requires-Dist: pytest-mock; extra == "testing"
Requires-Dist: tox; extra == "testing"
Provides-Extra: docs
Requires-Dist: sphinx; extra == "docs"
Requires-Dist: sphinx-immaterial; extra == "docs"
Provides-Extra: napari
Requires-Dist: napari-spotiflow; extra == "napari"
Provides-Extra: starfish
Requires-Dist: starfish; extra == "starfish"
